Metadata-Version: 2.1
Name: bc-en-de-coder
Version: 0.0.20
Summary: Data Protecting Package
Home-page: https://github.com/Distructor2404/bc-en-de-coder
Author: Abhishek Kumar Singh
Author-email: <abhishek123kumar123singh@gmail.com>
Keywords: python,Data secure,Encoder,Decoder,pdf reader
Classifier: Development Status :: 4 - Beta
Classifier: License :: OSI Approved :: MIT License
Classifier: Intended Audience :: Developers
Classifier: Programming Language :: Python :: 3
Classifier: Operating System :: Unix
Classifier: Operating System :: MacOS :: MacOS X
Classifier: Operating System :: Microsoft :: Windows
